{"latitude":46.785316,"longitude":-121.734973,"timezone":"America/Los_Angeles","currently":{"time":1545508189,"summary":"Mostly Cloudy","icon":"partly-cloudy-day","nearestStormDistance":0,"precipIntensity":0,"precipProbability":0,"temperature":29.97,"apparentTemperature":29.97,"dewPoint":25.96,"humidity":0.85,"pressure":1019.79,"windSpeed":1.69,"windGust":7.62,"windBearing":180,"cloudCover":0.93,"uvIndex":1,"visibility":3.2,"ozone":325.38},"daily":{"summary":"Snow (27–44 in.) throughout the week, with high temperatures bottoming out at 29°F on Tuesday.","icon":"snow","data":[{"time":1545465600,"summary":"Snow (5–8 in.) starting in the afternoon.","icon":"snow","sunriseTime":1545493855,"sunsetTime":1545524581,"moonPhase":0.51,"precipIntensity":0.0205,"precipIntensityMax":0.0928,"precipIntensityMaxTime":1545548400,"precipProbability":0.53,"precipAccumulation":4.46,"precipType":"snow","temperatureHigh":32.46,"temperatureHighTime":1545516000,"temperatureLow":27.58,"temperatureLowTime":1545580800,"apparentTemperatureHigh":32.3,"apparentTemperatureHighTime":1545512400,"apparentTemperatureLow":20.28,"apparentTemperatureLowTime":1545555600,"dewPoint":24.35,"humidity":0.91,"pressure":1020.07,"windSpeed":3.27,"windGust":22.14,"windGustTime":1545548400,"windBearing":127,"cloudCover":0.8,"uvIndex":1,"uvIndexTime":1545505200,"visibility":3.22,"ozone":333.22,"temperatureMin":19.58,"temperatureMinTime":1545465600,"temperatureMax":32.46,"temperatureMaxTime":1545516000,"apparentTemperatureMin":19.58,"apparentTemperatureMinTime":1545465600,"apparentTemperatureMax":32.3,"apparentTemperatureMaxTime":1545512400},{"time":1545552000,"summary":"Snow (13–21 in.) throughout the day.","icon":"snow","sunriseTime":1545580281,"sunsetTime":1545611014,"moonPhase":0.54,"precipIntensity":0.0787,"precipIntensityMax":0.1086,"precipIntensityMaxTime":1545584400,"precipProbability":0.94,"precipAccumulation":18.891,"precipType":"snow","temperatureHigh":29,"temperatureHighTime":1545577200,"temperatureLow":26.6,"temperatureLowTime":1545667200,"apparentTemperatureHigh":22.22,"apparentTemperatureHighTime":1545577200,"apparentTemperatureLow":20.92,"apparentTemperatureLowTime":1545667200,"dewPoint":28.11,"humidity":1,"pressure":1015.36,"windSpeed":6.77,"windGust":25.28,"windGustTime":1545555600,"windBearing":215,"cloudCover":0.99,"uvIndex":1,"uvIndexTime":1545591600,"visibility":0.43,"ozone":335.63,"temperatureMin":26.55,"temperatureMinTime":1545588000,"temperatureMax":30.78,"temperatureMaxTime":1545566400,"apparentTemperatureMin":18.55,"apparentTemperatureMinTime":1545588000,"apparentTemperatureMax":23.77,"apparentTemperatureMaxTime":1545570000},{"time":1545638400,"summary":"Snow (2–4 in.) until afternoon.","icon":"snow","sunriseTime":1545666703,"sunsetTime":1545697449,"moonPhase":0.58,"precipIntensity":0.0226,"precipIntensityMax":0.0582,"precipIntensityMaxTime":1545652800,"precipProbability":0.88,"precipAccumulation":5.332,"precipType":"snow","temperatureHigh":32.46,"temperatureHighTime":1545685200,"temperatureLow":23.31,"temperatureLowTime":1545753600,"apparentTemperatureHigh":32.46,"apparentTemperatureHighTime":1545685200,"apparentTemperatureLow":18.54,"apparentTemperatureLowTime":1545739200,"dewPoint":27.71,"humidity":0.99,"pressure":1017.73,"windSpeed":1,"windGust":10.93,"windGustTime":1545638400,"windBearing":185,"cloudCover":0.95,"uvIndex":1,"uvIndexTime":1545678000,"visibility":2.82,"ozone":329.54,"temperatureMin":25.03,"temperatureMinTime":1545706800,"temperatureMax":32.46,"temperatureMaxTime":1545685200,"apparentTemperatureMin":20.4,"apparentTemperatureMinTime":1545710400,"apparentTemperatureMax":32.46,"apparentTemperatureMaxTime":1545685200},{"time":1545724800,"summary":"Mostly cloudy throughout the day.","icon":"partly-cloudy-day","sunriseTime":1545753123,"sunsetTime":1545783887,"moonPhase":0.61,"precipIntensity":0.0011,"precipIntensityMax":0.0024,"precipIntensityMaxTime":1545724800,"precipProbability":0.35,"precipAccumulation":0.344,"precipType":"snow","temperatureHigh":29.27,"temperatureHighTime":1545771600,"temperatureLow":20.96,"temperatureLowTime":1545800400,"apparentTemperatureHigh":28.31,"apparentTemperatureHighTime":1545775200,"apparentTemperatureLow":15.46,"apparentTemperatureLowTime":1545804000,"dewPoint":22.32,"humidity":0.92,"pressure":1025.14,"windSpeed":1.85,"windGust":5.91,"windGustTime":1545771600,"windBearing":0,"cloudCover":0.78,"uvIndex":1,"uvIndexTime":1545764400,"visibility":5.86,"ozone":316,"temperatureMin":20.96,"temperatureMinTime":1545800400,"temperatureMax":29.27,"temperatureMaxTime":1545771600,"apparentTemperatureMin":15.46,"apparentTemperatureMinTime":1545804000,"apparentTemperatureMax":28.31,"apparentTemperatureMaxTime":1545775200},{"time":1545811200,"summary":"Snow (7–10 in.) throughout the day.","icon":"snow","sunriseTime":1545839540,"sunsetTime":1545870327,"moonPhase":0.65,"precipIntensity":0.0259,"precipIntensityMax":0.068,"precipIntensityMaxTime":1545868800,"precipProbability":0.69,"precipAccumulation":6.496,"precipType":"snow","temperatureHigh":29.94,"temperatureHighTime":1545865200,"temperatureLow":26.8,"temperatureLowTime":1545883200,"apparentTemperatureHigh":26.35,"apparentTemperatureHighTime":1545861600,"apparentTemperatureLow":23.12,"apparentTemperatureLowTime":1545883200,"dewPoint":24.71,"humidity":0.93,"pressure":1019.98,"windSpeed":2.32,"windGust":11.39,"windGustTime":1545868800,"windBearing":175,"cloudCover":0.95,"uvIndex":1,"uvIndexTime":1545850800,"visibility":3.12,"ozone":312,"temperatureMin":23.28,"temperatureMinTime":1545843600,"temperatureMax":29.94,"temperatureMaxTime":1545865200,"apparentTemperatureMin":19.95,"apparentTemperatureMinTime":1545847200,"apparentTemperatureMax":29.51,"apparentTemperatureMaxTime":1545894000},{"time":1545897600,"summary":"Snow (1–3 in.) in the morning.","icon":"snow","sunriseTime":1545925955,"sunsetTime":1545956770,"moonPhase":0.69,"precipIntensity":0.021,"precipIntensityMax":0.0562,"precipIntensityMaxTime":1545908400,"precipProbability":0.85,"precipAccumulation":5.022,"precipType":"snow","temperatureHigh":28.7,"temperatureHighTime":1545922800,"temperatureLow":21.13,"temperatureLowTime":1545980400,"apparentTemperatureHigh":28.7,"apparentTemperatureHighTime":1545922800,"apparentTemperatureLow":21.13,"apparentTemperatureLowTime":1545980400,"dewPoint":25.1,"humidity":0.96,"pressure":1022.98,"windSpeed":1.49,"windGust":7.34,"windGustTime":1545951600,"windBearing":289,"cloudCover":0.85,"uvIndex":1,"uvIndexTime":1545937200,"visibility":3.54,"ozone":362.95,"temperatureMin":21.13,"temperatureMinTime":1545980400,"temperatureMax":29.52,"temperatureMaxTime":1545897600,"apparentTemperatureMin":21.13,"apparentTemperatureMinTime":1545980400,"apparentTemperatureMax":29.52,"apparentTemperatureMaxTime":1545897600},{"time":1545984000,"summary":"Light snow (\u003c 1 in.) in the morning.","icon":"snow","sunriseTime":1546012366,"sunsetTime":1546043215,"moonPhase":0.73,"precipIntensity":0.0033,"precipIntensityMax":0.0089,"precipIntensityMaxTime":1546020000,"precipProbability":0.31,"precipAccumulation":0.978,"precipType":"snow","temperatureHigh":31.4,"temperatureHighTime":1546034400,"temperatureLow":23.4,"temperatureLowTime":1546056000,"apparentTemperatureHigh":31.4,"apparentTemperatureHighTime":1546034400,"apparentTemperatureLow":23.4,"apparentTemperatureLowTime":1546056000,"dewPoint":21.52,"humidity":0.87,"pressure":1028.12,"windSpeed":1.42,"windGust":4.74,"windGustTime":1546005600,"windBearing":71,"cloudCover":0.43,"uvIndex":1,"uvIndexTime":1546023600,"visibility":6.76,"ozone":352.31,"temperatureMin":21.61,"temperatureMinTime":1545984000,"temperatureMax":31.4,"temperatureMaxTime":1546034400,"apparentTemperatureMin":21.61,"apparentTemperatureMinTime":1545984000,"apparentTemperatureMax":31.4,"apparentTemperatureMaxTime":1546034400},{"time":1546070400,"summary":"Snow (1–3 in.) in the morning and overnight.","icon":"snow","sunriseTime":1546098775,"sunsetTime":1546129663,"moonPhase":0.76,"precipIntensity":0.0143,"precipIntensityMax":0.0306,"precipIntensityMaxTime":1546149600,"precipProbability":0.39,"precipAccumulation":2.729,"precipType":"snow","temperatureHigh":35.91,"temperatureHighTime":1546117200,"temperatureLow":31.35,"temperatureLowTime":1546182000,"apparentTemperatureHigh":35.91,"apparentTemperatureHighTime":1546117200,"apparentTemperatureLow":28.55,"apparentTemperatureLowTime":1546142400,"dewPoint":24.15,"humidity":0.78,"pressure":1026.44,"windSpeed":1.69,"windGust":5.91,"windGustTime":1546117200,"windBearing":29,"cloudCover":0.74,"uvIndex":1,"uvIndexTime":1546110000,"visibility":10,"ozone":318.19,"temperatureMin":25.66,"temperatureMinTime":1546070400,"temperatureMax":35.91,"temperatureMaxTime":1546117200,"apparentTemperatureMin":25.66,"apparentTemperatureMinTime":1546070400,"apparentTemperatureMax":35.91,"apparentTemperatureMaxTime":1546117200}]},"alerts":[{"title":"Winter Weather Advisory","regions":["West Slopes North Cascades and Passes","West Slopes North Central Cascades and Passes","West Slopes South Central Cascades and Passes"],"severity":"advisory","time":1545523200,"expires":1545609600,"description":"...WINTER WEATHER ADVISORY REMAINS IN EFFECT FROM 4 PM THIS AFTERNOON TO 4 PM PST SUNDAY ABOVE 2500 FEET... * WHAT...Snow expected above 2500 feet. 6 to 12 inches of accumulation at pass levels with up to 2 feet possible along higher peaks. * WHERE...Cascade mountains and valleys of Whatcom, Skagit, Snohomish, King, Pierce and Lewis Counties, including the Mount Baker Ski Area, Stevens Pass, Snoqualmie Pass, the Crystal Mountain Ski Area, and Paradise on Mount Rainier. * WHEN...From 4 PM Saturday to 4 PM PST Sunday. * ADDITIONAL DETAILS...Snow levels will rise on Sunday to around 3000-3500 feet. Hazardous travel conditions expected from time to time due to slick and snow covered roadways.\n","uri":"https://alerts.weather.gov/cap/wwacapget.php?x=WA125ACE931FA8.WinterWeatherAdvisory.125ACEB00A00WA.SEWWSWSEW.fb99a5cc59eeade49d25fbeaa49530c6"}],"flags":{"sources":["nearest-precip","nwspa","cmc","gfs","hrrr","icon","isd","madis","nam","sref","darksky"],"nearest-station":0.329,"units":"us"},"offset":-8}